[
  {
    "name_ru": "Узбекнефтегаз",
    "name_en": "Uzbekneftegaz JSC",
    "ticker": "UNEG",
    "isin": "UZ0000000001",
    "registration_no": "1000007",
    "market_type": "uzse",
    "sector": "Энергетика",
    "subsector": "Нефть и газ",
    "country": "UZ",
    "source_url": "https://uzse.uz",
    "is_active": true
  },
  {
    "name_ru": "Алмалыкский горно-металлургический комбинат",
    "name_en": "Almalyk Mining and Metallurgical Complex JSC",
    "ticker": "AGMK",
    "isin": "UZ0000000002",
    "registration_no": "1000008",
    "market_type": "uzse",
    "sector": "Металлургия",
    "subsector": "Цветные металлы",
    "country": "UZ",
    "source_url": "https://uzse.uz",
    "is_active": true
  },
  {
    "name_ru": "Узбекские авиалинии",
    "name_en": "Uzbekistan Airways JSC",
    "ticker": "UZAIRWAYS",
    "isin": "UZ0000000003",
    "registration_no": "1000009",
    "market_type": "uzse",
    "sector": "Транспорт",
    "subsector": "Авиаперевозки",
    "country": "UZ",
    "source_url": "https://uzse.uz",
    "is_active": true
  },
  {
    "name_ru": "Kapitalbank",
    "name_en": "Kapitalbank JSCB",
    "ticker": "KBANK",
    "isin": "UZ0000000004",
    "registration_no": "1000010",
    "market_type": "uzse",
    "sector": "Финансы",
    "subsector": "Банковские услуги",
    "country": "UZ",
    "source_url": "https://uzse.uz",
    "is_active": true
  },
  {
    "name_ru": "Национальный банк Узбекистана",
    "name_en": "National Bank of Uzbekistan JSC",
    "ticker": "NBU",
    "isin": "UZ0000000005",
    "registration_no": "1000011",
    "market_type": "uzse",
    "sector": "Финансы",
    "subsector": "Банковские услуги",
    "country": "UZ",
    "source_url": "https://uzse.uz",
    "is_active": true
  },
  {
    "name_ru": "Узбекистон темир йуллари",
    "name_en": "Uzbekistan Railways JSC",
    "ticker": "UTY",
    "isin": "UZ0000000006",
    "registration_no": "1000012",
    "market_type": "uzse",
    "sector": "Транспорт",
    "subsector": "Железнодорожный транспорт",
    "country": "UZ",
    "source_url": "https://uzse.uz",
    "is_active": true
  },
  {
    "name_ru": "Uztelecom",
    "name_en": "Uztelecom JSC",
    "ticker": "UTLC",
    "isin": "UZ0000000007",
    "registration_no": "1000013",
    "market_type": "uzse",
    "sector": "Телекоммуникации",
    "subsector": "Проводная связь",
    "country": "UZ",
    "source_url": "https://uzse.uz",
    "is_active": true
  },
  {
    "name_ru": "Ucell (Coscom LLC)",
    "name_en": "Ucell (Coscom LLC)",
    "ticker": "UCELL",
    "isin": "UZ0000000008",
    "registration_no": "1000014",
    "market_type": "uzse",
    "sector": "Телекоммуникации",
    "subsector": "Мобильная связь",
    "country": "UZ",
    "source_url": "https://uzse.uz",
    "is_active": true
  },
  {
    "name_ru": "Узбекэнерго",
    "name_en": "Uzbekenergo JSC",
    "ticker": "UZENERGY",
    "isin": "UZ0000000009",
    "registration_no": "1000015",
    "market_type": "uzse",
    "sector": "Коммунальные услуги",
    "subsector": "Электроэнергетика",
    "country": "UZ",
    "source_url": "https://uzse.uz",
    "is_active": true
  },
  {
    "name_ru": "Узбекхимпром",
    "name_en": "Uzkimyosanoat JSC",
    "ticker": "UZCHEM",
    "isin": "UZ0000000010",
    "registration_no": "1000016",
    "market_type": "uzse",
    "sector": "Промышленность",
    "subsector": "Химическая промышленность",
    "country": "UZ",
    "source_url": "https://uzse.uz",
    "is_active": true
  },
  {
    "name_ru": "Агробанк",
    "name_en": "Agrobank JSC",
    "ticker": "AGROB",
    "isin": "UZ0000000011",
    "registration_no": "1000017",
    "market_type": "uzse",
    "sector": "Финансы",
    "subsector": "Агропромышленное финансирование",
    "country": "UZ",
    "source_url": "https://uzse.uz",
    "is_active": true
  },
  {
    "name_ru": "Узфармпром",
    "name_en": "Uzfarmpharm JSC",
    "ticker": "UZPHARM",
    "isin": "UZ0000000012",
    "registration_no": "1000018",
    "market_type": "uzse",
    "sector": "Здравоохранение",
    "subsector": "Фармацевтика",
    "country": "UZ",
    "source_url": "https://uzse.uz",
    "is_active": true
  },
  {
    "name_ru": "Orient Finance",
    "name_en": "Orient Finance Leasing Company JSC",
    "ticker": "ORIENTFIN",
    "isin": "UZ0000000013",
    "registration_no": "1000019",
    "market_type": "uzse",
    "sector": "Финансы",
    "subsector": "Лизинг",
    "country": "UZ",
    "source_url": "https://uzse.uz",
    "is_active": true
  },
  {
    "name_ru": "Ipak Yoli Bank",
    "name_en": "Ipak Yoli Bank JSC",
    "ticker": "IPAKBANK",
    "isin": "UZ0000000014",
    "registration_no": "1000020",
    "market_type": "uzse",
    "sector": "Финансы",
    "subsector": "Банковские услуги",
    "country": "UZ",
    "source_url": "https://uzse.uz",
    "is_active": true
  },
  {
    "name_ru": "Узбуммаш",
    "name_en": "Uzbummash JSC",
    "ticker": "UZBMASH",
    "isin": "UZ0000000015",
    "registration_no": "1000021",
    "market_type": "uzse",
    "sector": "Промышленность",
    "subsector": "Машиностроение",
    "country": "UZ",
    "source_url": "https://uzse.uz",
    "is_active": true
  }
]